paillier/__init__.py
paillier/__version__.py
paillier/crypto.py
paillier/keygen.py
paillier/main.py
paillier/util/__init__.py
paillier/util/math_shortcuts.py
paillier/util/prime_generation.py
paillier/util/prime_test.py
paillier/util/timing.py
paillier/util/validation.py
rens_paillier-1.2.1.dist-info/LICENSE
rens_paillier-1.2.1.dist-info/METADATA
rens_paillier-1.2.1.dist-info/WHEEL
rens_paillier-1.2.1.dist-info/top_level.txt
rens_paillier-1.2.1.dist-info/RECORD
