Metadata-Version: 2.1
Name: rens-paillier
Version: 1.2.1
Summary: Paillier encryption
Home-page: https://gitlab.com/RensOliemans/paillier
Author: Rens Oliemans
Author-email: rens.oliemans@gmail.com
License: MIT
Download-URL: https://gitlab.com/RensOliemans/paillier/-/archive/master/paillier-master.tar.gz
Project-URL: Source, https://gitlab.com/RensOliemans/paillier
Project-URL: Tracker, https://gitlab.com/RensOliemans/paillier/-/issues
Project-URL: Documentation, https://gitlab.com/RensOliemans/paillier/-/wikis/home
Platform: UNKNOWN
Classifier: Development Status :: 5 - Production/Stable
Classifier: License :: OSI Approved :: MIT License
Classifier: Operating System :: OS Independent
Classifier: Programming Language :: Python :: 3.8
Classifier: Topic :: Security
Classifier: Topic :: Security :: Cryptography
Classifier: Intended Audience :: Science/Research
Requires-Python: >=3.8
